tc_redis/__init__.py
tc_redis/utils.py
tc_redis/result_storages/__init__.py
tc_redis/result_storages/redis_result_storage.py
tc_redis/storages/__init__.py
tc_redis/storages/redis_storage.py
vows/__init__.py
vows/redis_storage_vows.py
vows/fixtures/__init__.py
vows/fixtures/storage_fixtures.py
dffrntlab_tc_redis-2.1.2.dist-info/LICENSE
dffrntlab_tc_redis-2.1.2.dist-info/METADATA
dffrntlab_tc_redis-2.1.2.dist-info/WHEEL
dffrntlab_tc_redis-2.1.2.dist-info/top_level.txt
dffrntlab_tc_redis-2.1.2.dist-info/RECORD
