Metadata-Version: 2.1
Name: dffrntlab-tc-redis
Version: 2.1.2
Summary: Thumbor redis storage adapters
Home-page: https://github.com/thumbor-community/redis
Author: Thumbor Community
Author-email: UNKNOWN
License: MIT
Keywords: thumbor redis
Platform: UNKNOWN
Classifier: Development Status :: 5 - Production/Stable
Classifier: License :: OSI Approved :: MIT License
Classifier: Programming Language :: Python :: 2.7
Requires-Dist: dffrntlab-thumbor (<8.0.0,>=7.2.0)
Requires-Dist: redis-py-cluster (==1.3.5)
